Metadata-Version: 2.4
Name: iCCF
Version: 0.4.5
Summary: Analysis of CCF profiles and activity indicators
Author-email: João Faria <joao.faria@unige.ch>
License: MIT
Project-URL: Homepage, https://j-faria.github.io/iCCF/
Project-URL: Repository, https://github.com/j-faria/iCCF
Project-URL: Issues, https://github.com/j-faria/iCCF/issues
Classifier: Programming Language :: Python :: 3
Requires-Python: >=3.7
License-File: LICENSE
Requires-Dist: numpy
Requires-Dist: scipy
Requires-Dist: matplotlib
Requires-Dist: astropy
Requires-Dist: paramiko
Requires-Dist: tqdm
Dynamic: license-file
